genutm/__init__.py
genutm/cli.py
genutm/cloudinit.py
genutm/config.py
genutm/log.py
genutm/mkuser.py
genutm/utm.py
genutm/static/docker-compose.yml
genutm/static/qemu-img.Dockerfile
genutm-0.2.2.dist-info/entry_points.txt
genutm-0.2.2.dist-info/licenses/LICENSE
genutm-0.2.2.dist-info/WHEEL
genutm-0.2.2.dist-info/METADATA
genutm-0.2.2.dist-info/RECORD
