Metadata-Version: 2.4
Name: genutm
Version: 0.2.2
Summary: genutm
Author-email: gottaeat <eateing@loggedin.net>
Classifier: License :: OSI Approved :: GNU General Public License v3 or later (GPLv3+)
License-File: LICENSE
Requires-Dist: pycdlib >= 1.14.0
Requires-Dist: PyYAML >= 6.0.0
Requires-Dist: passlib >= 1.6.0
Project-URL: Home, https://github.com/gottaeat/genutm
